examples/__init__.py
examples/nmpc_rocket_2d/ModelBase.py
examples/nmpc_rocket_2d/Rocket.py
examples/nmpc_rocket_2d/__init__.py
examples/nmpc_rocket_2d/example.py
examples/nmpc_rocket_2d/plot_rocket.py
ocp_modules/__init__.py
ocp_modules/controllers/ControllerBase.py
ocp_modules/controllers/Lqr.py
ocp_modules/controllers/Nmpc.py
ocp_modules/controllers/RtiNmpc.py
ocp_modules/controllers/__init__.py
ocp_modules/modules/DirectMultipleShootingConstraints.py
ocp_modules/modules/InitialValueConstraints.py
ocp_modules/modules/LinearConstraint.py
ocp_modules/modules/OcpParams.py
ocp_modules/modules/OcpVars.py
ocp_modules/modules/QuaternionConsistencyContraint.py
ocp_modules/modules/TrackingCosts.py
ocp_modules/modules/__init__.py
ocp_modules/utils/__init__.py
ocp_modules/utils/graceful_interrupt_handler.py
ocp_modules/utils/linearize_casadi.py
ocp_modules/utils/mse.py
ocp_modules/utils/quaternion.py
ocp_modules/utils/runge_kutta_4.py
ocp_modules/utils/solver_compilation.py
ocp_modules-0.1.0.dist-info/LICENSE
ocp_modules-0.1.0.dist-info/METADATA
ocp_modules-0.1.0.dist-info/WHEEL
ocp_modules-0.1.0.dist-info/top_level.txt
ocp_modules-0.1.0.dist-info/RECORD
