Metadata-Version: 2.1
Name: ocp-modules
Version: 0.1.0
Summary: A library to assemble OCPs from modules
Home-page: https://github.com/schlagenhauf/ocp-modules
Author: Jonas Schlagenhauf
Author-email: schlagenhauf_github@mailbox.org
License: GNU General Public License
Platform: UNKNOWN
Classifier: Programming Language :: Python :: 3
Classifier: License :: OSI Approved :: GNU General Public License (GPL)
Classifier: Operating System :: OS Independent
Requires-Python: >=3.6
Requires-Dist: numpy
Requires-Dist: casadi
Requires-Dist: xarray
